meg_room/__init__.py
meg_room/_audio_system.py
meg_room/_eyetracker.py
meg_room/_photodiode.py
meg_room/_response_buttons.py
meg_room/_stim_pc.py
meg_room/room.py
meg_room/utils.py
meg_room-0.0.3.dist-info/LICENSE
meg_room-0.0.3.dist-info/METADATA
meg_room-0.0.3.dist-info/WHEEL
meg_room-0.0.3.dist-info/top_level.txt
meg_room-0.0.3.dist-info/RECORD
